lib_foo/__init__.py
lib_foo/core.py
lib_foo-1.0.0.dist-info/licenses/LICENSE
lib_foo-1.0.0.dist-info/METADATA
lib_foo-1.0.0.dist-info/WHEEL
lib_foo-1.0.0.dist-info/top_level.txt
lib_foo-1.0.0.dist-info/RECORD
