Metadata-Version: 2.4
Name: lib_foo
Version: 1.0.0
Summary: Tiny curl-like urgentcall library
Author-email: Artem Brunov <art.brnv@gmail.com>
License: MIT
Project-URL: Homepage, https://github.com/artbrnv/lib_foo
Requires-Python: >=3.8
License-File: LICENSE
Requires-Dist: requests
Dynamic: license-file
